ollama_rag_de/chat/__init__.py
ollama_rag_de/chat/router.py
ollama_rag_de/cli.py
ollama_rag_de/engine.py
ollama_rag_de/process_folder.py
ollama_rag_de/server.py
ollama_rag_de/settings.py
ollama_rag_de/util/__init__.py
ollama_rag_de/util/dataframes.py
ollama_rag_de/util/file.py
ollama_rag_de/vector_store.py
ollama_rag_de-0.1.0.dist-info/METADATA
ollama_rag_de-0.1.0.dist-info/WHEEL
ollama_rag_de-0.1.0.dist-info/entry_points.txt
ollama_rag_de-0.1.0.dist-info/RECORD
