Metadata-Version: 2.1
Name: ollama-rag-de
Version: 0.1.0
Summary: A tool to digest PDF files for Large Language Models and serving them via a REST API, including their source references.
License: Proprietary
Author: crs
Author-email: mail@christian-spaniol.de
Requires-Python: >=3.9,<3.12
Classifier: License :: Other/Proprietary License
Classifier: Programming Language :: Python :: 3
Classifier: Programming Language :: Python :: 3.9
Classifier: Programming Language :: Python :: 3.10
Classifier: Programming Language :: Python :: 3.11
Requires-Dist: click (>=8.1.7,<9.0.0)
Requires-Dist: fastapi (>=0.110.1,<0.111.0)
Requires-Dist: llama-index-embeddings-huggingface (>=0.2.0,<0.3.0)
Requires-Dist: llama-index-embeddings-ollama (>=0.1.2,<0.2.0)
Requires-Dist: llama-index-embeddings-openai (>=0.1.7,<0.2.0)
Requires-Dist: llama-index-llms-ollama (>=0.1.2,<0.2.0)
Requires-Dist: llama-index-llms-openai (>=0.1.14,<0.2.0)
Requires-Dist: llama-index-readers-smart-pdf-loader (>=0.1.3,<0.2.0)
Requires-Dist: llama-index-vector-stores-qdrant (>=0.1.6,<0.2.0)
Requires-Dist: python-dotenv (>=1.0.1,<2.0.0)
Requires-Dist: uvicorn (>=0.29.0,<0.30.0)
